{
  "schedule": [
    {
      "שם": "לב",
      "ראשון": "לילה",
      "שני": "ערב",
      "שלישי": "—",
      "רביעי": "לילה",
      "חמישי": "לילה",
      "שישי": "—",
      "שבת": "לילה",
      "סה״כ": 5
    },
    {
      "שם": "איתי",
      "ראשון": "לילה",
      "שני": "—",
      "שלישי": "—",
      "רביעי": "—",
      "חמישי": "—",
      "שישי": "בוקר",
      "שבת": "לילה",
      "סה״כ": 3
    },
    {
      "שם": "גיא",
      "ראשון": "—",
      "שני": "לילה",
      "שלישי": "לילה",
      "רביעי": "לילה",
      "חמישי": "—",
      "שישי": "לילה",
      "שבת": "ערב",
      "סה״כ": 5
    },
    {
      "שם": "אלינור",
      "ראשון": "—",
      "שני": "—",
      "שלישי": "לילה",
      "רביעי": "—",
      "חמישי": "—",
      "שישי": "לילה",
      "שבת": "ערב",
      "סה״כ": 3
    },
    {
      "שם": "שרית",
      "ראשון": "בוקר",
      "שני": "בוקר",
      "שלישי": "ערב",
      "רביעי": "בוקר",
      "חמישי": "בוקר",
      "שישי": "—",
      "שבת": "—",
      "סה״כ": 5
    },
    {
      "שם": "רונית",
      "ראשון": "—",
      "שני": "—",
      "שלישי": "—",
      "רביעי": "—",
      "חמישי": "—",
      "שישי": "—",
      "שבת": "—",
      "סה״כ": 0
    },
    {
      "שם": "שני",
      "ראשון": "ערב",
      "שני": "—",
      "שלישי": "—",
      "רביעי": "בוקר",
      "חמישי": "בוקר",
      "שישי": "ערב",
      "שבת": "בוקר",
      "סה״כ": 5
    },
    {
      "שם": "ריקי",
      "ראשון": "בוקר",
      "שני": "בוקר",
      "שלישי": "—",
      "רביעי": "—",
      "חמישי": "בוקר",
      "שישי": "—",
      "שבת": "—",
      "סה״כ": 3
    },
    {
      "שם": "טלי",
      "ראשון": "ערב",
      "שני": "בוקר",
      "שלישי": "בוקר",
      "רביעי": "ערב",
      "חמישי": "—",
      "שישי": "בוקר",
      "שבת": "—",
      "סה״כ": 5
    },
    {
      "שם": "סימה",
      "ראשון": "—",
      "שני": "ערב",
      "שלישי": "ערב",
      "רביעי": "—",
      "חמישי": "—",
      "שישי": "—",
      "שבת": "—",
      "סה״כ": 2
    },
    {
      "שם": "לירון",
      "ראשון": "—",
      "שני": "לילה",
      "שלישי": "בוקר",
      "רביעי": "בוקר",
      "חמישי": "—",
      "שישי": "ערב",
      "שבת": "בוקר",
      "סה״כ": 5
    }
  ],
  "twelve_hour": {
    "לירון_רביעי": false,
    "גיא_רביעי": false,
    "רונית_שישי": false,
    "איתי_שישי": false,
    "שני_שלישי": true,
    "לב_שלישי": true
  },
  "watcher": {
    "ראשון_בוקר": "שני",
    "ראשון_ערב": "שרית",
    "ראשון_לילה": "לב",
    "שני_בוקר": "שרית",
    "שני_ערב": "רונית",
    "שני_לילה": "לב",
    "שלישי_בוקר": "שני",
    "שלישי_ערב": "סימה",
    "שלישי_לילה": "לב",
    "רביעי_בוקר": "רונית",
    "רביעי_ערב": "טלי",
    "רביעי_לילה": "לב",
    "חמישי_בוקר": "שרית",
    "חמישי_ערב": "טלי",
    "חמישי_לילה": "לב",
    "שישי_בוקר": "איתי",
    "שישי_ערב": "שרית",
    "שישי_לילה": "איתי",
    "שבת_בוקר": "שרית",
    "שבת_ערב": "איתי",
    "שבת_לילה": "גיא"
  },
  "cell_notes": {},
  "week_label": "19-25\\7",
  "week_notes": ""
}